setup.cfg
setup.py
representor/__init__.py
representor/attributes.py
representor/base.py
representor/dom.py
representor/inputs.py
representor/media_types.py
representor/resource.py
representor/translator.py
representor/utils.py
representor/wrappers.py
representor.egg-info/PKG-INFO
representor.egg-info/SOURCES.txt
representor.egg-info/dependency_links.txt
representor.egg-info/top_level.txt
representor/adapters/__init__.py
representor/adapters/hal_json.py
representor/adapters/hale_json.py
representor/contrib/__init__.py
representor/contrib/browser.py
representor/contrib/maze_xml.py