Metadata-Version: 1.0
Name: representor
Version: 0.3.0
Summary: Generic interface for hypermedia messages
Home-page: https://github.com/the-hypermedia-project/representor-python/
Author: Stephen Mizell
Author-email: smizell@gmail.com
License: MIT
Platform: UNKNOWN
